notion_client/__init__.py
notion_client/api_endpoints.py
notion_client/client.py
notion_client/errors.py
notion_client/helpers.py
notion_client/logging.py
notion_client/py.typed
notion_client/typing.py
tests/__init__.py
tests/conftest.py
tests/test_client.py
tests/test_helpers.py
notionhq_client-0.6.0.dist-info/LICENSE
notionhq_client-0.6.0.dist-info/METADATA
notionhq_client-0.6.0.dist-info/WHEEL
notionhq_client-0.6.0.dist-info/top_level.txt
notionhq_client-0.6.0.dist-info/RECORD
