Metadata-Version: 2.1
Name: notionhq-client
Version: 0.6.0
Summary: Python client for the official Notion API
Home-page: https://github.com/ramnes/notion-sdk-py
Author: Guillaume Gelin
Author-email: contact@ramnes.eu
License: UNKNOWN
Platform: UNKNOWN
Classifier: Programming Language :: Python :: 3.7
Classifier: Programming Language :: Python :: 3.8
Classifier: Programming Language :: Python :: 3.9
Classifier: Development Status :: 4 - Beta
Classifier: License :: OSI Approved :: MIT License
Requires-Python: >=3.7, <4
